[
    {
        "id": 1,
        "name": "Samsung Galaxy A15",
        "brand": "Samsung",
        "price": 90000,
        "stock": 10,
        "image": "product-image.php?id=1",
        "description": "Un smartphone Android fiable pour les appels, les réseaux sociaux, la photo et le travail quotidien.",
        "memory": "128 Go",
        "ram": "4 Go",
        "battery": "5000 mAh",
        "camera": "50 MP",
        "warranty": "7 jours",
        "trending": true,
        "promo": false
    },
    {
        "id": 2,
        "name": "Samsung Galaxy A25 5G",
        "brand": "Samsung",
        "price": 165000,
        "stock": 6,
        "image": "product-image.php?id=2",
        "description": "Un modèle équilibré avec bonne autonomie, écran confortable et stockage généreux.",
        "memory": "128 Go",
        "ram": "6 Go",
        "battery": "5000 mAh",
        "camera": "50 MP",
        "warranty": "7 jours",
        "trending": true,
        "promo": true
    },
    {
        "id": 3,
        "name": "Samsung Galaxy A35 5G",
        "brand": "Samsung",
        "price": 235000,
        "stock": 4,
        "image": "product-image.php?id=3",
        "description": "Un téléphone moderne pensé pour les utilisateurs qui veulent fluidité, photo et batterie solide.",
        "memory": "256 Go",
        "ram": "8 Go",
        "battery": "5000 mAh",
        "camera": "50 MP",
        "warranty": "7 jours",
        "trending": true,
        "promo": false
    },
    {
        "id": 4,
        "name": "Samsung Galaxy S23 FE",
        "brand": "Samsung",
        "price": 420000,
        "stock": 2,
        "image": "product-image.php?id=4",
        "description": "Un appareil performant pour vidéo, multitâche, jeux légers et usage intensif.",
        "memory": "256 Go",
        "ram": "8 Go",
        "battery": "4500 mAh",
        "camera": "50 MP",
        "warranty": "7 jours",
        "trending": true,
        "promo": false
    },
    {
        "id": 5,
        "name": "Tecno Spark 20",
        "brand": "Tecno",
        "price": 78000,
        "stock": 14,
        "image": "product-image.php?id=5",
        "description": "Un smartphone Android fiable pour les appels, les réseaux sociaux, la photo et le travail quotidien.",
        "memory": "128 Go",
        "ram": "4 Go",
        "battery": "5000 mAh",
        "camera": "50 MP",
        "warranty": "7 jours",
        "trending": true,
        "promo": true
    },
    {
        "id": 6,
        "name": "Tecno Camon 20",
        "brand": "Tecno",
        "price": 105000,
        "stock": 7,
        "image": "product-image.php?id=6",
        "description": "Un modèle équilibré avec bonne autonomie, écran confortable et stockage généreux.",
        "memory": "256 Go",
        "ram": "8 Go",
        "battery": "5000 mAh",
        "camera": "64 MP",
        "warranty": "7 jours",
        "trending": false,
        "promo": false
    },
    {
        "id": 7,
        "name": "Tecno Camon 30",
        "brand": "Tecno",
        "price": 145000,
        "stock": 6,
        "image": "product-image.php?id=7",
        "description": "Un téléphone moderne pensé pour les utilisateurs qui veulent fluidité, photo et batterie solide.",
        "memory": "256 Go",
        "ram": "8 Go",
        "battery": "5000 mAh",
        "camera": "50 MP",
        "warranty": "7 jours",
        "trending": true,
        "promo": true
    },
    {
        "id": 8,
        "name": "Tecno Pova 6 Pro",
        "brand": "Tecno",
        "price": 190000,
        "stock": 4,
        "image": "product-image.php?id=8",
        "description": "Un appareil performant pour vidéo, multitâche, jeux légers et usage intensif.",
        "memory": "256 Go",
        "ram": "8 Go",
        "battery": "6000 mAh",
        "camera": "108 MP",
        "warranty": "7 jours",
        "trending": true,
        "promo": false
    },
    {
        "id": 9,
        "name": "Infinix Hot 40",
        "brand": "Infinix",
        "price": 85000,
        "stock": 8,
        "image": "product-image.php?id=9",
        "description": "Un smartphone Android fiable pour les appels, les réseaux sociaux, la photo et le travail quotidien.",
        "memory": "128 Go",
        "ram": "8 Go",
        "battery": "5000 mAh",
        "camera": "50 MP",
        "warranty": "7 jours",
        "trending": true,
        "promo": false
    },
    {
        "id": 10,
        "name": "Infinix Note 30",
        "brand": "Infinix",
        "price": 125000,
        "stock": 4,
        "image": "product-image.php?id=10",
        "description": "Un modèle équilibré avec bonne autonomie, écran confortable et stockage généreux.",
        "memory": "256 Go",
        "ram": "8 Go",
        "battery": "5000 mAh",
        "camera": "64 MP",
        "warranty": "7 jours",
        "trending": true,
        "promo": false
    },
    {
        "id": 11,
        "name": "Infinix Zero 30",
        "brand": "Infinix",
        "price": 185000,
        "stock": 5,
        "image": "product-image.php?id=11",
        "description": "Un téléphone moderne pensé pour les utilisateurs qui veulent fluidité, photo et batterie solide.",
        "memory": "256 Go",
        "ram": "12 Go",
        "battery": "5000 mAh",
        "camera": "108 MP",
        "warranty": "7 jours",
        "trending": true,
        "promo": true
    },
    {
        "id": 12,
        "name": "Infinix Smart 8",
        "brand": "Infinix",
        "price": 62000,
        "stock": 16,
        "image": "product-image.php?id=12",
        "description": "Un appareil performant pour vidéo, multitâche, jeux légers et usage intensif.",
        "memory": "64 Go",
        "ram": "3 Go",
        "battery": "5000 mAh",
        "camera": "13 MP",
        "warranty": "7 jours",
        "trending": false,
        "promo": true
    },
    {
        "id": 13,
        "name": "Xiaomi Redmi 13C",
        "brand": "Xiaomi",
        "price": 95000,
        "stock": 6,
        "image": "product-image.php?id=13",
        "description": "Un smartphone Android fiable pour les appels, les réseaux sociaux, la photo et le travail quotidien.",
        "memory": "128 Go",
        "ram": "6 Go",
        "battery": "5000 mAh",
        "camera": "50 MP",
        "warranty": "7 jours",
        "trending": false,
        "promo": true
    },
    {
        "id": 14,
        "name": "Xiaomi Redmi Note 12",
        "brand": "Xiaomi",
        "price": 135000,
        "stock": 3,
        "image": "product-image.php?id=14",
        "description": "Un modèle équilibré avec bonne autonomie, écran confortable et stockage généreux.",
        "memory": "128 Go",
        "ram": "8 Go",
        "battery": "5000 mAh",
        "camera": "50 MP",
        "warranty": "7 jours",
        "trending": true,
        "promo": true
    },
    {
        "id": 15,
        "name": "Xiaomi Redmi Note 13",
        "brand": "Xiaomi",
        "price": 165000,
        "stock": 7,
        "image": "product-image.php?id=15",
        "description": "Un téléphone moderne pensé pour les utilisateurs qui veulent fluidité, photo et batterie solide.",
        "memory": "256 Go",
        "ram": "8 Go",
        "battery": "5000 mAh",
        "camera": "108 MP",
        "warranty": "7 jours",
        "trending": true,
        "promo": false
    },
    {
        "id": 16,
        "name": "Xiaomi Poco X6",
        "brand": "Xiaomi",
        "price": 245000,
        "stock": 3,
        "image": "product-image.php?id=16",
        "description": "Un appareil performant pour vidéo, multitâche, jeux légers et usage intensif.",
        "memory": "256 Go",
        "ram": "8 Go",
        "battery": "5100 mAh",
        "camera": "64 MP",
        "warranty": "7 jours",
        "trending": true,
        "promo": false
    },
    {
        "id": 17,
        "name": "Oppo A58",
        "brand": "Oppo",
        "price": 118000,
        "stock": 5,
        "image": "product-image.php?id=17",
        "description": "Un smartphone Android fiable pour les appels, les réseaux sociaux, la photo et le travail quotidien.",
        "memory": "128 Go",
        "ram": "6 Go",
        "battery": "5000 mAh",
        "camera": "50 MP",
        "warranty": "7 jours",
        "trending": false,
        "promo": false
    },
    {
        "id": 18,
        "name": "Oppo A78",
        "brand": "Oppo",
        "price": 145000,
        "stock": 2,
        "image": "product-image.php?id=18",
        "description": "Un modèle équilibré avec bonne autonomie, écran confortable et stockage généreux.",
        "memory": "256 Go",
        "ram": "8 Go",
        "battery": "5000 mAh",
        "camera": "50 MP",
        "warranty": "7 jours",
        "trending": false,
        "promo": true
    },
    {
        "id": 19,
        "name": "Oppo Reno 10",
        "brand": "Oppo",
        "price": 290000,
        "stock": 3,
        "image": "product-image.php?id=19",
        "description": "Un téléphone moderne pensé pour les utilisateurs qui veulent fluidité, photo et batterie solide.",
        "memory": "256 Go",
        "ram": "8 Go",
        "battery": "5000 mAh",
        "camera": "64 MP",
        "warranty": "7 jours",
        "trending": true,
        "promo": false
    },
    {
        "id": 20,
        "name": "Oppo Reno 11F",
        "brand": "Oppo",
        "price": 230000,
        "stock": 4,
        "image": "product-image.php?id=20",
        "description": "Un appareil performant pour vidéo, multitâche, jeux légers et usage intensif.",
        "memory": "256 Go",
        "ram": "8 Go",
        "battery": "5000 mAh",
        "camera": "64 MP",
        "warranty": "7 jours",
        "trending": true,
        "promo": true
    },
    {
        "id": 21,
        "name": "Itel A70",
        "brand": "Itel",
        "price": 52000,
        "stock": 20,
        "image": "product-image.php?id=21",
        "description": "Un smartphone Android fiable pour les appels, les réseaux sociaux, la photo et le travail quotidien.",
        "memory": "128 Go",
        "ram": "4 Go",
        "battery": "5000 mAh",
        "camera": "13 MP",
        "warranty": "7 jours",
        "trending": true,
        "promo": true
    },
    {
        "id": 22,
        "name": "Itel S23",
        "brand": "Itel",
        "price": 68000,
        "stock": 12,
        "image": "product-image.php?id=22",
        "description": "Un modèle équilibré avec bonne autonomie, écran confortable et stockage généreux.",
        "memory": "128 Go",
        "ram": "8 Go",
        "battery": "5000 mAh",
        "camera": "50 MP",
        "warranty": "7 jours",
        "trending": false,
        "promo": true
    },
    {
        "id": 23,
        "name": "Itel P55",
        "brand": "Itel",
        "price": 76000,
        "stock": 9,
        "image": "product-image.php?id=23",
        "description": "Un téléphone moderne pensé pour les utilisateurs qui veulent fluidité, photo et batterie solide.",
        "memory": "128 Go",
        "ram": "4 Go",
        "battery": "5000 mAh",
        "camera": "50 MP",
        "warranty": "7 jours",
        "trending": false,
        "promo": false
    },
    {
        "id": 24,
        "name": "Vivo Y17s",
        "brand": "Vivo",
        "price": 98000,
        "stock": 8,
        "image": "product-image.php?id=24",
        "description": "Un appareil performant pour vidéo, multitâche, jeux légers et usage intensif.",
        "memory": "128 Go",
        "ram": "4 Go",
        "battery": "5000 mAh",
        "camera": "50 MP",
        "warranty": "7 jours",
        "trending": false,
        "promo": true
    },
    {
        "id": 25,
        "name": "Vivo V29 Lite",
        "brand": "Vivo",
        "price": 210000,
        "stock": 3,
        "image": "product-image.php?id=25",
        "description": "Un smartphone Android fiable pour les appels, les réseaux sociaux, la photo et le travail quotidien.",
        "memory": "256 Go",
        "ram": "8 Go",
        "battery": "5000 mAh",
        "camera": "64 MP",
        "warranty": "7 jours",
        "trending": true,
        "promo": false
    },
    {
        "id": 26,
        "name": "Realme C55",
        "brand": "Realme",
        "price": 115000,
        "stock": 6,
        "image": "product-image.php?id=26",
        "description": "Un modèle équilibré avec bonne autonomie, écran confortable et stockage généreux.",
        "memory": "128 Go",
        "ram": "8 Go",
        "battery": "5000 mAh",
        "camera": "64 MP",
        "warranty": "7 jours",
        "trending": false,
        "promo": true
    },
    {
        "id": 27,
        "name": "Realme 11 Pro",
        "brand": "Realme",
        "price": 260000,
        "stock": 3,
        "image": "product-image.php?id=27",
        "description": "Un téléphone moderne pensé pour les utilisateurs qui veulent fluidité, photo et batterie solide.",
        "memory": "256 Go",
        "ram": "8 Go",
        "battery": "5000 mAh",
        "camera": "100 MP",
        "warranty": "7 jours",
        "trending": true,
        "promo": false
    },
    {
        "id": 28,
        "name": "Nokia G22",
        "brand": "Nokia",
        "price": 98000,
        "stock": 5,
        "image": "product-image.php?id=28",
        "description": "Un appareil performant pour vidéo, multitâche, jeux légers et usage intensif.",
        "memory": "128 Go",
        "ram": "4 Go",
        "battery": "5050 mAh",
        "camera": "50 MP",
        "warranty": "7 jours",
        "trending": false,
        "promo": false
    },
    {
        "id": 29,
        "name": "Nokia C32",
        "brand": "Nokia",
        "price": 72000,
        "stock": 10,
        "image": "product-image.php?id=29",
        "description": "Un smartphone Android fiable pour les appels, les réseaux sociaux, la photo et le travail quotidien.",
        "memory": "64 Go",
        "ram": "4 Go",
        "battery": "5050 mAh",
        "camera": "50 MP",
        "warranty": "7 jours",
        "trending": false,
        "promo": true
    },
    {
        "id": 30,
        "name": "Motorola Moto G54",
        "brand": "Motorola",
        "price": 145000,
        "stock": 5,
        "image": "product-image.php?id=30",
        "description": "Un modèle équilibré avec bonne autonomie, écran confortable et stockage généreux.",
        "memory": "256 Go",
        "ram": "8 Go",
        "battery": "5000 mAh",
        "camera": "50 MP",
        "warranty": "7 jours",
        "trending": true,
        "promo": false
    },
    {
        "id": 31,
        "name": "Motorola Edge 40",
        "brand": "Motorola",
        "price": 330000,
        "stock": 2,
        "image": "product-image.php?id=31",
        "description": "Un téléphone moderne pensé pour les utilisateurs qui veulent fluidité, photo et batterie solide.",
        "memory": "256 Go",
        "ram": "8 Go",
        "battery": "4400 mAh",
        "camera": "50 MP",
        "warranty": "7 jours",
        "trending": true,
        "promo": false
    },
    {
        "id": 32,
        "name": "Honor X8a",
        "brand": "Honor",
        "price": 135000,
        "stock": 5,
        "image": "product-image.php?id=32",
        "description": "Un appareil performant pour vidéo, multitâche, jeux légers et usage intensif.",
        "memory": "128 Go",
        "ram": "6 Go",
        "battery": "4500 mAh",
        "camera": "100 MP",
        "warranty": "7 jours",
        "trending": false,
        "promo": true
    },
    {
        "id": 33,
        "name": "Honor 90 Lite",
        "brand": "Honor",
        "price": 185000,
        "stock": 4,
        "image": "product-image.php?id=33",
        "description": "Un smartphone Android fiable pour les appels, les réseaux sociaux, la photo et le travail quotidien.",
        "memory": "256 Go",
        "ram": "8 Go",
        "battery": "4500 mAh",
        "camera": "100 MP",
        "warranty": "7 jours",
        "trending": true,
        "promo": false
    },
    {
        "id": 34,
        "name": "Huawei Nova 11i",
        "brand": "Huawei",
        "price": 190000,
        "stock": 3,
        "image": "product-image.php?id=34",
        "description": "Un modèle équilibré avec bonne autonomie, écran confortable et stockage généreux.",
        "memory": "128 Go",
        "ram": "8 Go",
        "battery": "5000 mAh",
        "camera": "48 MP",
        "warranty": "7 jours",
        "trending": false,
        "promo": false
    },
    {
        "id": 35,
        "name": "Huawei P60 Pro",
        "brand": "Huawei",
        "price": 520000,
        "stock": 1,
        "image": "product-image.php?id=35",
        "description": "Un téléphone moderne pensé pour les utilisateurs qui veulent fluidité, photo et batterie solide.",
        "memory": "256 Go",
        "ram": "8 Go",
        "battery": "4815 mAh",
        "camera": "48 MP",
        "warranty": "7 jours",
        "trending": true,
        "promo": false
    },
    {
        "id": 36,
        "name": "OnePlus Nord CE 3 Lite",
        "brand": "OnePlus",
        "price": 220000,
        "stock": 3,
        "image": "product-image.php?id=36",
        "description": "Un appareil performant pour vidéo, multitâche, jeux légers et usage intensif.",
        "memory": "256 Go",
        "ram": "8 Go",
        "battery": "5000 mAh",
        "camera": "108 MP",
        "warranty": "7 jours",
        "trending": true,
        "promo": true
    },
    {
        "id": 37,
        "name": "OnePlus 12R",
        "brand": "OnePlus",
        "price": 455000,
        "stock": 2,
        "image": "product-image.php?id=37",
        "description": "Un smartphone Android fiable pour les appels, les réseaux sociaux, la photo et le travail quotidien.",
        "memory": "256 Go",
        "ram": "16 Go",
        "battery": "5500 mAh",
        "camera": "50 MP",
        "warranty": "7 jours",
        "trending": true,
        "promo": false
    },
    {
        "id": 38,
        "name": "Google Pixel 7a",
        "brand": "Google Pixel",
        "price": 285000,
        "stock": 3,
        "image": "product-image.php?id=38",
        "description": "Un modèle équilibré avec bonne autonomie, écran confortable et stockage généreux.",
        "memory": "128 Go",
        "ram": "8 Go",
        "battery": "4385 mAh",
        "camera": "64 MP",
        "warranty": "7 jours",
        "trending": true,
        "promo": false
    },
    {
        "id": 39,
        "name": "Google Pixel 8",
        "brand": "Google Pixel",
        "price": 470000,
        "stock": 2,
        "image": "product-image.php?id=39",
        "description": "Un téléphone moderne pensé pour les utilisateurs qui veulent fluidité, photo et batterie solide.",
        "memory": "128 Go",
        "ram": "8 Go",
        "battery": "4575 mAh",
        "camera": "50 MP",
        "warranty": "7 jours",
        "trending": true,
        "promo": false
    },
    {
        "id": 40,
        "name": "Nothing Phone 2a",
        "brand": "Nothing",
        "price": 250000,
        "stock": 3,
        "image": "product-image.php?id=40",
        "description": "Un appareil performant pour vidéo, multitâche, jeux légers et usage intensif.",
        "memory": "128 Go",
        "ram": "8 Go",
        "battery": "5000 mAh",
        "camera": "50 MP",
        "warranty": "7 jours",
        "trending": true,
        "promo": true
    },
    {
        "id": 41,
        "name": "Sony Xperia 10 V",
        "brand": "Sony",
        "price": 315000,
        "stock": 2,
        "image": "product-image.php?id=41",
        "description": "Un smartphone Android fiable pour les appels, les réseaux sociaux, la photo et le travail quotidien.",
        "memory": "128 Go",
        "ram": "6 Go",
        "battery": "5000 mAh",
        "camera": "48 MP",
        "warranty": "7 jours",
        "trending": false,
        "promo": false
    },
    {
        "id": 42,
        "name": "Asus ROG Phone 7",
        "brand": "Asus",
        "price": 590000,
        "stock": 1,
        "image": "product-image.php?id=42",
        "description": "Un modèle équilibré avec bonne autonomie, écran confortable et stockage généreux.",
        "memory": "512 Go",
        "ram": "16 Go",
        "battery": "6000 mAh",
        "camera": "50 MP",
        "warranty": "7 jours",
        "trending": true,
        "promo": false
    },
    {
        "id": 43,
        "name": "TCL 40 SE",
        "brand": "TCL",
        "price": 89000,
        "stock": 7,
        "image": "product-image.php?id=43",
        "description": "Un téléphone moderne pensé pour les utilisateurs qui veulent fluidité, photo et batterie solide.",
        "memory": "128 Go",
        "ram": "6 Go",
        "battery": "5010 mAh",
        "camera": "50 MP",
        "warranty": "7 jours",
        "trending": false,
        "promo": true
    },
    {
        "id": 44,
        "name": "ZTE Blade V50",
        "brand": "ZTE",
        "price": 92000,
        "stock": 6,
        "image": "product-image.php?id=44",
        "description": "Un appareil performant pour vidéo, multitâche, jeux légers et usage intensif.",
        "memory": "128 Go",
        "ram": "6 Go",
        "battery": "5000 mAh",
        "camera": "50 MP",
        "warranty": "7 jours",
        "trending": false,
        "promo": false
    },
    {
        "id": 45,
        "name": "Blackview A96",
        "brand": "Blackview",
        "price": 120000,
        "stock": 4,
        "image": "product-image.php?id=45",
        "description": "Un smartphone Android fiable pour les appels, les réseaux sociaux, la photo et le travail quotidien.",
        "memory": "256 Go",
        "ram": "8 Go",
        "battery": "4380 mAh",
        "camera": "48 MP",
        "warranty": "7 jours",
        "trending": false,
        "promo": true
    },
    {
        "id": 46,
        "name": "Ulefone Armor X12",
        "brand": "Ulefone",
        "price": 105000,
        "stock": 3,
        "image": "product-image.php?id=46",
        "description": "Un modèle équilibré avec bonne autonomie, écran confortable et stockage généreux.",
        "memory": "64 Go",
        "ram": "3 Go",
        "battery": "4860 mAh",
        "camera": "13 MP",
        "warranty": "7 jours",
        "trending": false,
        "promo": false
    },
    {
        "id": 47,
        "name": "Doogee Smini",
        "brand": "Doogee",
        "price": 125000,
        "stock": 3,
        "image": "product-image.php?id=47",
        "description": "Un téléphone moderne pensé pour les utilisateurs qui veulent fluidité, photo et batterie solide.",
        "memory": "256 Go",
        "ram": "8 Go",
        "battery": "3000 mAh",
        "camera": "50 MP",
        "warranty": "7 jours",
        "trending": false,
        "promo": false
    },
    {
        "id": 48,
        "name": "Oukitel WP28",
        "brand": "Oukitel",
        "price": 115000,
        "stock": 5,
        "image": "product-image.php?id=48",
        "description": "Un appareil performant pour vidéo, multitâche, jeux légers et usage intensif.",
        "memory": "256 Go",
        "ram": "8 Go",
        "battery": "10600 mAh",
        "camera": "48 MP",
        "warranty": "7 jours",
        "trending": false,
        "promo": true
    },
    {
        "id": 49,
        "name": "Umidigi G5",
        "brand": "Umidigi",
        "price": 82000,
        "stock": 6,
        "image": "product-image.php?id=49",
        "description": "Un smartphone Android fiable pour les appels, les réseaux sociaux, la photo et le travail quotidien.",
        "memory": "128 Go",
        "ram": "8 Go",
        "battery": "5000 mAh",
        "camera": "50 MP",
        "warranty": "7 jours",
        "trending": false,
        "promo": true
    },
    {
        "id": 50,
        "name": "Cubot KingKong 9",
        "brand": "Cubot",
        "price": 160000,
        "stock": 2,
        "image": "product-image.php?id=50",
        "description": "Un modèle équilibré avec bonne autonomie, écran confortable et stockage généreux.",
        "memory": "256 Go",
        "ram": "12 Go",
        "battery": "10600 mAh",
        "camera": "100 MP",
        "warranty": "7 jours",
        "trending": false,
        "promo": false
    },
    {
        "id": 51,
        "name": "Meizu 21",
        "brand": "Meizu",
        "price": 430000,
        "stock": 1,
        "image": "product-image.php?id=51",
        "description": "Un téléphone moderne pensé pour les utilisateurs qui veulent fluidité, photo et batterie solide.",
        "memory": "256 Go",
        "ram": "12 Go",
        "battery": "4800 mAh",
        "camera": "200 MP",
        "warranty": "7 jours",
        "trending": true,
        "promo": false
    },
    {
        "id": 52,
        "name": "Alcatel 1SE",
        "brand": "Alcatel",
        "price": 58000,
        "stock": 8,
        "image": "product-image.php?id=52",
        "description": "Un appareil performant pour vidéo, multitâche, jeux légers et usage intensif.",
        "memory": "32 Go",
        "ram": "3 Go",
        "battery": "4000 mAh",
        "camera": "13 MP",
        "warranty": "7 jours",
        "trending": false,
        "promo": true
    }
]